{
    "presets": [
        {
            "name": "Mac Book Pro 16",
            "width": 13.5,
            "height": 8.5,
            "pxWidth": 3456,
            "pxHeight": 2234,
            "ppi": 254
        },
        {
            "name": "Pangyo LG Monitor 27",
            "width": 26.38,
            "height": 14.76,
            "pxWidth": 3840,
            "pxHeight": 2160,
            "ppi": null
        },
        {
            "name": "Mountain View Frame",
            "width": 58.8,
            "height": 31,
            "pxWidth": 3840,
            "pxHeight": 2160,
            "ppi": null
        },
        {
            "name": "Apple Studio 27",
            "width": 23.54,
            "height": 13.23,
            "pxWidth": 5120,
            "pxHeight": 2880,
            "ppi": 218
        },
        {
            "name": "Samsung Serif 55",
            "width": 47.95,
            "height": 26.97,
            "pxWidth": 3840,
            "pxHeight": 2160,
            "ppi": 80
        },
        {
            "name": "Mountain View Dell 32",
            "width": 27.44,
            "height": 15.43,
            "pxWidth": 3840,
            "pxHeight": 2160,
            "ppi": 140
        }
    ]
} 